odoo/addons/easy_my_coop_ch/README.rst
odoo/addons/easy_my_coop_ch/__init__.py
odoo/addons/easy_my_coop_ch/__manifest__.py
odoo/addons/easy_my_coop_ch/i18n/easy_my_coop_ch.pot
odoo/addons/easy_my_coop_ch/models/__init__.py
odoo/addons/easy_my_coop_ch/models/partner.py
odoo/addons/easy_my_coop_ch/models/subscription_request.py
odoo/addons/easy_my_coop_ch/readme/CONTRIBUTORS.rst
odoo/addons/easy_my_coop_ch/readme/DESCRIPTION.rst
odoo/addons/easy_my_coop_ch/static/description/index.html
odoo/addons/easy_my_coop_ch/views/subscription_template.xml
odoo12_addon_easy_my_coop_ch-12.0.1.2.0.dist-info/METADATA
odoo12_addon_easy_my_coop_ch-12.0.1.2.0.dist-info/WHEEL
odoo12_addon_easy_my_coop_ch-12.0.1.2.0.dist-info/top_level.txt
odoo12_addon_easy_my_coop_ch-12.0.1.2.0.dist-info/RECORD
